{"id":"3734","round":"1","name":"2026년 함평군 협회장배 배드민턴 대회","status":"종료","startDate":"2026.02.28","endDate":"2026.02.28","host":"함평군","venue":"대동문화체육센터","detailUrl":"https://sfa.bkplay.kr/tournament/detail.do?tnmtId=3734&tnmtRound=1","provinceOrgId":"15","provinceName":"전남","draws":[{"drawId":"88516-109283","tournamentId":"3734","tournamentName":"2026년 함평군 협회장배 배드민턴 대회","tournamentStatus":"종료","tournamentStartDate":"2026.02.28","tournamentEndDate":"2026.02.28","tournamentVenue":"대동문화체육센터","category":{"event":"남복","age":"40대A그룹","level":"통합급수","teamCount":5,"playingCategoryId":"88516","title":"남복 40대A그룹 통합급수","sourceUrl":"https://sfa.bkplay.kr/tournament/qualifierMatch?tnmtId=3734&playingCategoryId=88516&groupId=109283"},"groupName":"1조","groupId":"109283","matchDate":"02월28일(토)","venue":"대동문화체육센터","standings":[{"rank":1,"teamName":"함평천지클럽","players":["김제곤","박춘일"],"wins":3,"losses":1,"game":{"scored":3,"conceded":1,"diff":2},"point":{"scored":97,"conceded":62,"diff":35},"includesClub":false,"isCombinedClub":false},{"rank":2,"teamName":"함평학다리클럽&함평희망클럽","players":["이형주","윤광현"],"wins":3,"losses":1,"game":{"scored":3,"conceded":1,"diff":2},"point":{"scored":97,"conceded":71,"diff":26},"includesClub":false,"isCombinedClub":false},{"rank":3,"teamName":"함평천지클럽","players":["신동선","이계문"],"wins":3,"losses":1,"game":{"scored":2,"conceded":1,"diff":1},"point":{"scored":60,"conceded":58,"diff":2},"includesClub":false,"isCombinedClub":false},{"rank":4,"teamName":"함평천지클럽","players":["김대원","김석준"],"wins":1,"losses":3,"game":{"scored":1,"conceded":3,"diff":-2},"point":{"scored":65,"conceded":93,"diff":-28},"includesClub":false,"isCombinedClub":false},{"rank":5,"teamName":"함평천지클럽&함평함평클럽","players":["김성언","김현"],"wins":0,"losses":4,"game":{"scored":0,"conceded":3,"diff":-3},"point":{"scored":40,"conceded":75,"diff":-35},"includesClub":false,"isCombinedClub":false}],"matches":[{"date":"2026.02.28(토)","time":"15:15","court":"9코트","matchNo":"4번","title":"개인전 남복 40대A그룹 통합급수 - 풀리그","status":"경기종료","firstTeam":"함평천지클럽 (김제곤 / 박춘일)","secondTeam":"함평천지클럽 (김대원 / 김석준)","score":"25 : 17","text":"경기종료 개인전 남복 40대A그룹 통합급수 - 풀리그 함평천지클럽 김제곤 / 박춘일 25 : 17 함평천지클럽 김대원 / 김석준 2026.02.28(토) 15:15 9코트 4번","includesClub":false},{"date":"2026.02.28(토)","time":"15:15","court":"10코트","matchNo":"4번","title":"개인전 남복 40대A그룹 통합급수 - 풀리그","status":"경기종료","firstTeam":"함평천지클럽 (신동선 / 이계문)","secondTeam":"함평학다리클럽&함평희망클럽 (이형주 / 윤광현)","score":"25 : 22","text":"경기종료 개인전 남복 40대A그룹 통합급수 - 풀리그 함평천지클럽 신동선 / 이계문 25 : 22 함평학다리클럽&함평희망클럽 이형주 / 윤광현 2026.02.28(토) 15:15 10코트 4번","includesClub":false},{"date":"2026.02.28(토)","time":"15:30","court":"9코트","matchNo":"5번","title":"개인전 남복 40대A그룹 통합급수 - 풀리그","status":"경기종료","firstTeam":"함평천지클럽&함평함평클럽 (김성언 / 김현)","secondTeam":"함평학다리클럽&함평희망클럽 (이형주 / 윤광현)","score":"12 : 25","text":"경기종료 개인전 남복 40대A그룹 통합급수 - 풀리그 함평천지클럽&함평함평클럽 김성언 / 김현 12 : 25 함평학다리클럽&함평희망클럽 이형주 / 윤광현 2026.02.28(토) 15:30 9코트 5번","includesClub":false},{"date":"2026.02.28(토)","time":"15:30","court":"10코트","matchNo":"5번","title":"개인전 남복 40대A그룹 통합급수 - 풀리그","status":"경기종료","firstTeam":"함평천지클럽 (김제곤 / 박춘일)","secondTeam":"함평천지클럽 (신동선 / 이계문)","score":"25 : 10","text":"경기종료 개인전 남복 40대A그룹 통합급수 - 풀리그 함평천지클럽 김제곤 / 박춘일 25 : 10 함평천지클럽 신동선 / 이계문 2026.02.28(토) 15:30 10코트 5번","includesClub":false},{"date":"2026.02.28(토)","time":"15:45","court":"10코트","matchNo":"6번","title":"개인전 남복 40대A그룹 통합급수 - 풀리그","status":"경기종료","firstTeam":"함평천지클럽 (신동선 / 이계문)","secondTeam":"함평천지클럽&함평함평클럽 (김성언 / 김현)","score":"0 : 0","text":"경기종료 개인전 남복 40대A그룹 통합급수 - 풀리그 함평천지클럽 신동선 / 이계문 0 : 0 함평천지클럽&함평함평클럽 김성언 / 김현 2026.02.28(토) 15:45 10코트 6번","includesClub":false},{"date":"2026.02.28(토)","time":"16:00","court":"9코트","matchNo":"7번","title":"개인전 남복 40대A그룹 통합급수 - 풀리그","status":"경기종료","firstTeam":"함평천지클럽&함평함평클럽 (김성언 / 김현)","secondTeam":"함평천지클럽 (김제곤 / 박춘일)","score":"10 : 25","text":"경기종료 개인전 남복 40대A그룹 통합급수 - 풀리그 함평천지클럽&함평함평클럽 김성언 / 김현 10 : 25 함평천지클럽 김제곤 / 박춘일 2026.02.28(토) 16:00 9코트 7번","includesClub":false},{"date":"2026.02.28(토)","time":"16:00","court":"10코트","matchNo":"7번","title":"개인전 남복 40대A그룹 통합급수 - 풀리그","status":"경기종료","firstTeam":"함평천지클럽 (김대원 / 김석준)","secondTeam":"함평천지클럽 (신동선 / 이계문)","score":"11 : 25","text":"경기종료 개인전 남복 40대A그룹 통합급수 - 풀리그 함평천지클럽 김대원 / 김석준 11 : 25 함평천지클럽 신동선 / 이계문 2026.02.28(토) 16:00 10코트 7번","includesClub":false},{"date":"2026.02.28(토)","time":"16:15","court":"9코트","matchNo":"8번","title":"개인전 남복 40대A그룹 통합급수 - 풀리그","status":"경기종료","firstTeam":"함평천지클럽 (김대원 / 김석준)","secondTeam":"함평천지클럽&함평함평클럽 (김성언 / 김현)","score":"25 : 18","text":"경기종료 개인전 남복 40대A그룹 통합급수 - 풀리그 함평천지클럽 김대원 / 김석준 25 : 18 함평천지클럽&함평함평클럽 김성언 / 김현 2026.02.28(토) 16:15 9코트 8번","includesClub":false},{"date":"2026.02.28(토)","time":"16:15","court":"10코트","matchNo":"8번","title":"개인전 남복 40대A그룹 통합급수 - 풀리그","status":"경기종료","firstTeam":"함평학다리클럽&함평희망클럽 (이형주 / 윤광현)","secondTeam":"함평천지클럽 (김제곤 / 박춘일)","score":"25 : 22","text":"경기종료 개인전 남복 40대A그룹 통합급수 - 풀리그 함평학다리클럽&함평희망클럽 이형주 / 윤광현 25 : 22 함평천지클럽 김제곤 / 박춘일 2026.02.28(토) 16:15 10코트 8번","includesClub":false},{"date":"2026.02.28(토)","time":"16:30","court":"6코트","matchNo":"9번","title":"개인전 남복 40대A그룹 통합급수 - 풀리그","status":"경기종료","firstTeam":"함평학다리클럽&함평희망클럽 (이형주 / 윤광현)","secondTeam":"함평천지클럽 (김대원 / 김석준)","score":"25 : 12","text":"경기종료 개인전 남복 40대A그룹 통합급수 - 풀리그 함평학다리클럽&함평희망클럽 이형주 / 윤광현 25 : 12 함평천지클럽 김대원 / 김석준 2026.02.28(토) 16:30 6코트 9번","includesClub":false}],"sourceUrl":"https://sfa.bkplay.kr/tournament/qualifierMatch?tnmtId=3734&playingCategoryId=88516&groupId=109283"},{"drawId":"88514-109282","tournamentId":"3734","tournamentName":"2026년 함평군 협회장배 배드민턴 대회","tournamentStatus":"종료","tournamentStartDate":"2026.02.28","tournamentEndDate":"2026.02.28","tournamentVenue":"대동문화체육센터","category":{"event":"남복","age":"40미만A그룹","level":"통합급수","teamCount":3,"playingCategoryId":"88514","title":"남복 40미만A그룹 통합급수","sourceUrl":"https://sfa.bkplay.kr/tournament/qualifierMatch?tnmtId=3734&playingCategoryId=88514&groupId=109282"},"groupName":"1조","groupId":"109282","matchDate":"02월28일(토)","venue":"대동문화체육센터","standings":[{"rank":1,"teamName":"함평함평클럽&함평희망클럽","players":["임영인","윤영찬"],"wins":2,"losses":0,"game":{"scored":2,"conceded":0,"diff":2},"point":{"scored":50,"conceded":30,"diff":20},"includesClub":false,"isCombinedClub":false},{"rank":2,"teamName":"함평함평클럽&함평해월클럽","players":["노강현","박래현"],"wins":1,"losses":1,"game":{"scored":1,"conceded":1,"diff":0},"point":{"scored":44,"conceded":39,"diff":5},"includesClub":false,"isCombinedClub":false},{"rank":3,"teamName":"함평함평클럽","players":["이동호","정민규"],"wins":0,"losses":2,"game":{"scored":0,"conceded":2,"diff":-2},"point":{"scored":25,"conceded":50,"diff":-25},"includesClub":false,"isCombinedClub":false}],"matches":[{"date":"2026.02.28(토)","time":"15:15","court":"5코트","matchNo":"4번","title":"개인전 남복 40미만A그룹 통합급수 - 풀리그","status":"경기종료","firstTeam":"함평함평클럽&함평희망클럽 (임영인 / 윤영찬)","secondTeam":"함평함평클럽 (이동호 / 정민규)","score":"25 : 11","text":"경기종료 개인전 남복 40미만A그룹 통합급수 - 풀리그 함평함평클럽&함평희망클럽 임영인 / 윤영찬 25 : 11 함평함평클럽 이동호 / 정민규 2026.02.28(토) 15:15 5코트 4번","includesClub":false},{"date":"2026.02.28(토)","time":"15:30","court":"5코트","matchNo":"5번","title":"개인전 남복 40미만A그룹 통합급수 - 풀리그","status":"경기종료","firstTeam":"함평함평클럽 (이동호 / 정민규)","secondTeam":"함평함평클럽&함평해월클럽 (노강현 / 박래현)","score":"14 : 25","text":"경기종료 개인전 남복 40미만A그룹 통합급수 - 풀리그 함평함평클럽 이동호 / 정민규 14 : 25 함평함평클럽&함평해월클럽 노강현 / 박래현 2026.02.28(토) 15:30 5코트 5번","includesClub":false},{"date":"2026.02.28(토)","time":"15:45","court":"6코트","matchNo":"6번","title":"개인전 남복 40미만A그룹 통합급수 - 풀리그","status":"경기종료","firstTeam":"함평함평클럽&함평해월클럽 (노강현 / 박래현)","secondTeam":"함평함평클럽&함평희망클럽 (임영인 / 윤영찬)","score":"19 : 25","text":"경기종료 개인전 남복 40미만A그룹 통합급수 - 풀리그 함평함평클럽&함평해월클럽 노강현 / 박래현 19 : 25 함평함평클럽&함평희망클럽 임영인 / 윤영찬 2026.02.28(토) 15:45 6코트 6번","includesClub":false}],"sourceUrl":"https://sfa.bkplay.kr/tournament/qualifierMatch?tnmtId=3734&playingCategoryId=88514&groupId=109282"},{"drawId":"88837-109285","tournamentId":"3734","tournamentName":"2026년 함평군 협회장배 배드민턴 대회","tournamentStatus":"종료","tournamentStartDate":"2026.02.28","tournamentEndDate":"2026.02.28","tournamentVenue":"대동문화체육센터","category":{"event":"남복","age":"40미만B그룹 1조","level":"통합급수","teamCount":4,"playingCategoryId":"88837","title":"남복 40미만B그룹 1조 통합급수","sourceUrl":"https://sfa.bkplay.kr/tournament/qualifierMatch?tnmtId=3734&playingCategoryId=88837&groupId=109285"},"groupName":"1조","groupId":"109285","matchDate":"02월28일(토)","venue":"대동문화체육센터","standings":[{"rank":1,"teamName":"함평학다리클럽&함평천지클럽","players":["전대원","이유범"],"wins":2,"losses":1,"game":{"scored":2,"conceded":1,"diff":1},"point":{"scored":74,"conceded":65,"diff":9},"includesClub":false,"isCombinedClub":false},{"rank":2,"teamName":"함평천지클럽","players":["김창선","나광문"],"wins":2,"losses":1,"game":{"scored":2,"conceded":1,"diff":1},"point":{"scored":72,"conceded":66,"diff":6},"includesClub":false,"isCombinedClub":false},{"rank":3,"teamName":"함평희망클럽","players":["윤여창","이태성"],"wins":2,"losses":1,"game":{"scored":2,"conceded":1,"diff":1},"point":{"scored":71,"conceded":73,"diff":-2},"includesClub":false,"isCombinedClub":false},{"rank":4,"teamName":"함평함평클럽","players":["정인준","문민후"],"wins":0,"losses":3,"game":{"scored":0,"conceded":3,"diff":-3},"point":{"scored":62,"conceded":75,"diff":-13},"includesClub":false,"isCombinedClub":false}],"matches":[{"date":"2026.02.28(토)","time":"15:45","court":"5코트","matchNo":"6번","title":"개인전 남복 40미만B그룹 1조 통합급수 - 풀리그","status":"경기종료","firstTeam":"함평천지클럽 (김창선 / 나광문)","secondTeam":"함평학다리클럽&함평천지클럽 (전대원 / 이유범)","score":"22 : 25","text":"경기종료 개인전 남복 40미만B그룹 1조 통합급수 - 풀리그 함평천지클럽 김창선 / 나광문 22 : 25 함평학다리클럽&함평천지클럽 전대원 / 이유범 2026.02.28(토) 15:45 5코트 6번","includesClub":false},{"date":"2026.02.28(토)","time":"15:45","court":"1코트","matchNo":"6번","title":"개인전 남복 40미만B그룹 1조 통합급수 - 풀리그","status":"경기종료","firstTeam":"함평함평클럽 (정인준 / 문민후)","secondTeam":"함평희망클럽 (윤여창 / 이태성)","score":"24 : 25","text":"경기종료 개인전 남복 40미만B그룹 1조 통합급수 - 풀리그 함평함평클럽 정인준 / 문민후 24 : 25 함평희망클럽 윤여창 / 이태성 2026.02.28(토) 15:45 1코트 6번","includesClub":false},{"date":"2026.02.28(토)","time":"16:00","court":"1코트","matchNo":"7번","title":"개인전 남복 40미만B그룹 1조 통합급수 - 풀리그","status":"경기종료","firstTeam":"함평학다리클럽&함평천지클럽 (전대원 / 이유범)","secondTeam":"함평함평클럽 (정인준 / 문민후)","score":"25 : 18","text":"경기종료 개인전 남복 40미만B그룹 1조 통합급수 - 풀리그 함평학다리클럽&함평천지클럽 전대원 / 이유범 25 : 18 함평함평클럽 정인준 / 문민후 2026.02.28(토) 16:00 1코트 7번","includesClub":false},{"date":"2026.02.28(토)","time":"16:00","court":"5코트","matchNo":"7번","title":"개인전 남복 40미만B그룹 1조 통합급수 - 풀리그","status":"경기종료","firstTeam":"함평천지클럽 (김창선 / 나광문)","secondTeam":"함평희망클럽 (윤여창 / 이태성)","score":"25 : 21","text":"경기종료 개인전 남복 40미만B그룹 1조 통합급수 - 풀리그 함평천지클럽 김창선 / 나광문 25 : 21 함평희망클럽 윤여창 / 이태성 2026.02.28(토) 16:00 5코트 7번","includesClub":false},{"date":"2026.02.28(토)","time":"16:15","court":"5코트","matchNo":"8번","title":"개인전 남복 40미만B그룹 1조 통합급수 - 풀리그","status":"경기종료","firstTeam":"함평함평클럽 (정인준 / 문민후)","secondTeam":"함평천지클럽 (김창선 / 나광문)","score":"20 : 25","text":"경기종료 개인전 남복 40미만B그룹 1조 통합급수 - 풀리그 함평함평클럽 정인준 / 문민후 20 : 25 함평천지클럽 김창선 / 나광문 2026.02.28(토) 16:15 5코트 8번","includesClub":false},{"date":"2026.02.28(토)","time":"16:15","court":"1코트","matchNo":"8번","title":"개인전 남복 40미만B그룹 1조 통합급수 - 풀리그","status":"경기종료","firstTeam":"함평학다리클럽&함평천지클럽 (전대원 / 이유범)","secondTeam":"함평희망클럽 (윤여창 / 이태성)","score":"24 : 25","text":"경기종료 개인전 남복 40미만B그룹 1조 통합급수 - 풀리그 함평학다리클럽&함평천지클럽 전대원 / 이유범 24 : 25 함평희망클럽 윤여창 / 이태성 2026.02.28(토) 16:15 1코트 8번","includesClub":false}],"sourceUrl":"https://sfa.bkplay.kr/tournament/qualifierMatch?tnmtId=3734&playingCategoryId=88837&groupId=109285"},{"drawId":"88838-109286","tournamentId":"3734","tournamentName":"2026년 함평군 협회장배 배드민턴 대회","tournamentStatus":"종료","tournamentStartDate":"2026.02.28","tournamentEndDate":"2026.02.28","tournamentVenue":"대동문화체육센터","category":{"event":"남복","age":"40미만B그룹 2조","level":"통합급수","teamCount":3,"playingCategoryId":"88838","title":"남복 40미만B그룹 2조 통합급수","sourceUrl":"https://sfa.bkplay.kr/tournament/qualifierMatch?tnmtId=3734&playingCategoryId=88838&groupId=109286"},"groupName":"1조","groupId":"109286","matchDate":"02월28일(토)","venue":"대동문화체육센터","standings":[{"rank":1,"teamName":"함평희망클럽","players":["박대현","윤정원"],"wins":2,"losses":0,"game":{"scored":2,"conceded":0,"diff":2},"point":{"scored":50,"conceded":27,"diff":23},"includesClub":false,"isCombinedClub":false},{"rank":2,"teamName":"함평천지클럽","players":["이기남","김용환"],"wins":1,"losses":1,"game":{"scored":1,"conceded":1,"diff":0},"point":{"scored":42,"conceded":36,"diff":6},"includesClub":false,"isCombinedClub":false},{"rank":3,"teamName":"함평함평클럽","players":["이도연","문종훈"],"wins":0,"losses":2,"game":{"scored":0,"conceded":2,"diff":-2},"point":{"scored":21,"conceded":50,"diff":-29},"includesClub":false,"isCombinedClub":false}],"matches":[{"date":"2026.02.28(토)","time":"15:30","court":"6코트","matchNo":"5번","title":"개인전 남복 40미만B그룹 2조 통합급수 - 풀리그","status":"경기종료","firstTeam":"함평함평클럽 (이도연 / 문종훈)","secondTeam":"함평희망클럽 (박대현 / 윤정원)","score":"10 : 25","text":"경기종료 개인전 남복 40미만B그룹 2조 통합급수 - 풀리그 함평함평클럽 이도연 / 문종훈 10 : 25 함평희망클럽 박대현 / 윤정원 2026.02.28(토) 15:30 6코트 5번","includesClub":false},{"date":"2026.02.28(토)","time":"15:45","court":"2코트","matchNo":"6번","title":"개인전 남복 40미만B그룹 2조 통합급수 - 풀리그","status":"경기종료","firstTeam":"함평희망클럽 (박대현 / 윤정원)","secondTeam":"함평천지클럽 (이기남 / 김용환)","score":"25 : 17","text":"경기종료 개인전 남복 40미만B그룹 2조 통합급수 - 풀리그 함평희망클럽 박대현 / 윤정원 25 : 17 함평천지클럽 이기남 / 김용환 2026.02.28(토) 15:45 2코트 6번","includesClub":false},{"date":"2026.02.28(토)","time":"16:15","court":"6코트","matchNo":"8번","title":"개인전 남복 40미만B그룹 2조 통합급수 - 풀리그","status":"경기종료","firstTeam":"함평천지클럽 (이기남 / 김용환)","secondTeam":"함평함평클럽 (이도연 / 문종훈)","score":"25 : 11","text":"경기종료 개인전 남복 40미만B그룹 2조 통합급수 - 풀리그 함평천지클럽 이기남 / 김용환 25 : 11 함평함평클럽 이도연 / 문종훈 2026.02.28(토) 16:15 6코트 8번","includesClub":false}],"sourceUrl":"https://sfa.bkplay.kr/tournament/qualifierMatch?tnmtId=3734&playingCategoryId=88838&groupId=109286"},{"drawId":"88530-109284","tournamentId":"3734","tournamentName":"2026년 함평군 협회장배 배드민턴 대회","tournamentStatus":"종료","tournamentStartDate":"2026.02.28","tournamentEndDate":"2026.02.28","tournamentVenue":"대동문화체육센터","category":{"event":"남복","age":"45미만","level":"초심","teamCount":5,"playingCategoryId":"88530","title":"남복 45미만 초심","sourceUrl":"https://sfa.bkplay.kr/tournament/qualifierMatch?tnmtId=3734&playingCategoryId=88530&groupId=109284"},"groupName":"1조","groupId":"109284","matchDate":"02월28일(토)","venue":"대동문화체육센터","standings":[{"rank":1,"teamName":"함평학다리클럽&함평천지클럽","players":["전대진","이유범"],"wins":4,"losses":0,"game":{"scored":4,"conceded":0,"diff":4},"point":{"scored":100,"conceded":72,"diff":28},"includesClub":false,"isCombinedClub":false},{"rank":2,"teamName":"함평함평클럽","players":["홍승우","신윤결"],"wins":3,"losses":1,"game":{"scored":3,"conceded":1,"diff":2},"point":{"scored":99,"conceded":63,"diff":36},"includesClub":false,"isCombinedClub":false},{"rank":3,"teamName":"함평희망클럽","players":["윤여선","나광렬"],"wins":1,"losses":3,"game":{"scored":1,"conceded":3,"diff":-2},"point":{"scored":76,"conceded":90,"diff":-14},"includesClub":false,"isCombinedClub":false},{"rank":4,"teamName":"함평학다리클럽","players":["김시민","조은호"],"wins":1,"losses":3,"game":{"scored":1,"conceded":3,"diff":-2},"point":{"scored":68,"conceded":96,"diff":-28},"includesClub":false,"isCombinedClub":false},{"rank":5,"teamName":"함평희망클럽","players":["김범수","윤석찬"],"wins":1,"losses":3,"game":{"scored":1,"conceded":3,"diff":-2},"point":{"scored":66,"conceded":88,"diff":-22},"includesClub":false,"isCombinedClub":false}],"matches":[{"date":"2026.02.28(토)","time":"13:00","court":"2코트","matchNo":"1번","title":"개인전 남복 45미만 초심 - 풀리그","status":"경기종료","firstTeam":"함평희망클럽 (김범수 / 윤석찬)","secondTeam":"함평희망클럽 (윤여선 / 나광렬)","score":"15 : 25","text":"경기종료 개인전 남복 45미만 초심 - 풀리그 함평희망클럽 김범수 / 윤석찬 15 : 25 함평희망클럽 윤여선 / 나광렬 2026.02.28(토) 13:00 2코트 1번","includesClub":false},{"date":"2026.02.28(토)","time":"13:00","court":"1코트","matchNo":"1번","title":"개인전 남복 45미만 초심 - 풀리그","status":"경기종료","firstTeam":"함평함평클럽 (홍승우 / 신윤결)","secondTeam":"함평학다리클럽&함평천지클럽 (전대진 / 이유범)","score":"24 : 25","text":"경기종료 개인전 남복 45미만 초심 - 풀리그 함평함평클럽 홍승우 / 신윤결 24 : 25 함평학다리클럽&함평천지클럽 전대진 / 이유범 2026.02.28(토) 13:00 1코트 1번","includesClub":false},{"date":"2026.02.28(토)","time":"13:15","court":"2코트","matchNo":"2번","title":"개인전 남복 45미만 초심 - 풀리그","status":"경기종료","firstTeam":"함평희망클럽 (윤여선 / 나광렬)","secondTeam":"함평학다리클럽&함평천지클럽 (전대진 / 이유범)","score":"15 : 25","text":"경기종료 개인전 남복 45미만 초심 - 풀리그 함평희망클럽 윤여선 / 나광렬 15 : 25 함평학다리클럽&함평천지클럽 전대진 / 이유범 2026.02.28(토) 13:15 2코트 2번","includesClub":false},{"date":"2026.02.28(토)","time":"13:15","court":"1코트","matchNo":"2번","title":"개인전 남복 45미만 초심 - 풀리그","status":"경기종료","firstTeam":"함평희망클럽 (김범수 / 윤석찬)","secondTeam":"함평학다리클럽 (김시민 / 조은호)","score":"25 : 13","text":"경기종료 개인전 남복 45미만 초심 - 풀리그 함평희망클럽 김범수 / 윤석찬 25 : 13 함평학다리클럽 김시민 / 조은호 2026.02.28(토) 13:15 1코트 2번","includesClub":false},{"date":"2026.02.28(토)","time":"15:00","court":"2코트","matchNo":"3번","title":"개인전 남복 45미만 초심 - 풀리그","status":"경기종료","firstTeam":"함평학다리클럽&함평천지클럽 (전대진 / 이유범)","secondTeam":"함평학다리클럽 (김시민 / 조은호)","score":"25 : 17","text":"경기종료 개인전 남복 45미만 초심 - 풀리그 함평학다리클럽&함평천지클럽 전대진 / 이유범 25 : 17 함평학다리클럽 김시민 / 조은호 2026.02.28(토) 15:00 2코트 3번","includesClub":false},{"date":"2026.02.28(토)","time":"15:00","court":"1코트","matchNo":"3번","title":"개인전 남복 45미만 초심 - 풀리그","status":"경기종료","firstTeam":"함평희망클럽 (윤여선 / 나광렬)","secondTeam":"함평함평클럽 (홍승우 / 신윤결)","score":"15 : 25","text":"경기종료 개인전 남복 45미만 초심 - 풀리그 함평희망클럽 윤여선 / 나광렬 15 : 25 함평함평클럽 홍승우 / 신윤결 2026.02.28(토) 15:00 1코트 3번","includesClub":false},{"date":"2026.02.28(토)","time":"15:15","court":"1코트","matchNo":"4번","title":"개인전 남복 45미만 초심 - 풀리그","status":"경기종료","firstTeam":"함평학다리클럽&함평천지클럽 (전대진 / 이유범)","secondTeam":"함평희망클럽 (김범수 / 윤석찬)","score":"25 : 16","text":"경기종료 개인전 남복 45미만 초심 - 풀리그 함평학다리클럽&함평천지클럽 전대진 / 이유범 25 : 16 함평희망클럽 김범수 / 윤석찬 2026.02.28(토) 15:15 1코트 4번","includesClub":false},{"date":"2026.02.28(토)","time":"15:15","court":"2코트","matchNo":"4번","title":"개인전 남복 45미만 초심 - 풀리그","status":"경기종료","firstTeam":"함평학다리클럽 (김시민 / 조은호)","secondTeam":"함평함평클럽 (홍승우 / 신윤결)","score":"13 : 25","text":"경기종료 개인전 남복 45미만 초심 - 풀리그 함평학다리클럽 김시민 / 조은호 13 : 25 함평함평클럽 홍승우 / 신윤결 2026.02.28(토) 15:15 2코트 4번","includesClub":false},{"date":"2026.02.28(토)","time":"15:30","court":"1코트","matchNo":"5번","title":"개인전 남복 45미만 초심 - 풀리그","status":"경기종료","firstTeam":"함평학다리클럽 (김시민 / 조은호)","secondTeam":"함평희망클럽 (윤여선 / 나광렬)","score":"25 : 21","text":"경기종료 개인전 남복 45미만 초심 - 풀리그 함평학다리클럽 김시민 / 조은호 25 : 21 함평희망클럽 윤여선 / 나광렬 2026.02.28(토) 15:30 1코트 5번","includesClub":false},{"date":"2026.02.28(토)","time":"15:30","court":"2코트","matchNo":"5번","title":"개인전 남복 45미만 초심 - 풀리그","status":"경기종료","firstTeam":"함평함평클럽 (홍승우 / 신윤결)","secondTeam":"함평희망클럽 (김범수 / 윤석찬)","score":"25 : 10","text":"경기종료 개인전 남복 45미만 초심 - 풀리그 함평함평클럽 홍승우 / 신윤결 25 : 10 함평희망클럽 김범수 / 윤석찬 2026.02.28(토) 15:30 2코트 5번","includesClub":false}],"sourceUrl":"https://sfa.bkplay.kr/tournament/qualifierMatch?tnmtId=3734&playingCategoryId=88530&groupId=109284"},{"drawId":"88524-109298","tournamentId":"3734","tournamentName":"2026년 함평군 협회장배 배드민턴 대회","tournamentStatus":"종료","tournamentStartDate":"2026.02.28","tournamentEndDate":"2026.02.28","tournamentVenue":"대동문화체육센터","category":{"event":"남복","age":"50대B그룹","level":"통합급수","teamCount":5,"playingCategoryId":"88524","title":"남복 50대B그룹 통합급수","sourceUrl":"https://sfa.bkplay.kr/tournament/qualifierMatch?tnmtId=3734&playingCategoryId=88524&groupId=109298"},"groupName":"1조","groupId":"109298","matchDate":"02월28일(토)","venue":"대동문화체육센터","standings":[{"rank":1,"teamName":"함평해월클럽","players":["박내주","김희옥"],"wins":4,"losses":0,"game":{"scored":4,"conceded":0,"diff":4},"point":{"scored":100,"conceded":44,"diff":56},"includesClub":false,"isCombinedClub":false},{"rank":2,"teamName":"함평천지클럽&함평희망클럽","players":["김정수","김희수"],"wins":2,"losses":2,"game":{"scored":2,"conceded":2,"diff":0},"point":{"scored":90,"conceded":79,"diff":11},"includesClub":false,"isCombinedClub":false},{"rank":3,"teamName":"함평해월클럽","players":["오상열","이재두"],"wins":2,"losses":2,"game":{"scored":2,"conceded":2,"diff":0},"point":{"scored":82,"conceded":84,"diff":-2},"includesClub":false,"isCombinedClub":false},{"rank":4,"teamName":"함평함평클럽","players":["김남현","신고균"],"wins":2,"losses":2,"game":{"scored":2,"conceded":2,"diff":0},"point":{"scored":71,"conceded":80,"diff":-9},"includesClub":false,"isCombinedClub":false},{"rank":5,"teamName":"함평희망클럽","players":["이재국","정동섭"],"wins":0,"losses":4,"game":{"scored":0,"conceded":4,"diff":-4},"point":{"scored":44,"conceded":100,"diff":-56},"includesClub":false,"isCombinedClub":false}],"matches":[{"date":"2026.02.28(토)","time":"15:15","court":"6코트","matchNo":"4번","title":"개인전 남복 50대B그룹 통합급수 - 풀리그","status":"경기종료","firstTeam":"함평함평클럽 (김남현 / 신고균)","secondTeam":"함평해월클럽 (박내주 / 김희옥)","score":"8 : 25","text":"경기종료 개인전 남복 50대B그룹 통합급수 - 풀리그 함평함평클럽 김남현 / 신고균 8 : 25 함평해월클럽 박내주 / 김희옥 2026.02.28(토) 15:15 6코트 4번","includesClub":false},{"date":"2026.02.28(토)","time":"15:15","court":"7코트","matchNo":"4번","title":"개인전 남복 50대B그룹 통합급수 - 풀리그","status":"경기종료","firstTeam":"함평희망클럽 (이재국 / 정동섭)","secondTeam":"함평해월클럽 (오상열 / 이재두)","score":"21 : 25","text":"경기종료 개인전 남복 50대B그룹 통합급수 - 풀리그 함평희망클럽 이재국 / 정동섭 21 : 25 함평해월클럽 오상열 / 이재두 2026.02.28(토) 15:15 7코트 4번","includesClub":false},{"date":"2026.02.28(토)","time":"15:45","court":"7코트","matchNo":"6번","title":"개인전 남복 50대B그룹 통합급수 - 풀리그","status":"경기종료","firstTeam":"함평해월클럽 (오상열 / 이재두)","secondTeam":"함평해월클럽 (박내주 / 김희옥)","score":"10 : 25","text":"경기종료 개인전 남복 50대B그룹 통합급수 - 풀리그 함평해월클럽 오상열 / 이재두 10 : 25 함평해월클럽 박내주 / 김희옥 2026.02.28(토) 15:45 7코트 6번","includesClub":false},{"date":"2026.02.28(토)","time":"15:45","court":"4코트","matchNo":"6번","title":"개인전 남복 50대B그룹 통합급수 - 풀리그","status":"경기종료","firstTeam":"함평희망클럽 (이재국 / 정동섭)","secondTeam":"함평천지클럽&함평희망클럽 (김정수 / 김희수)","score":"7 : 25","text":"경기종료 개인전 남복 50대B그룹 통합급수 - 풀리그 함평희망클럽 이재국 / 정동섭 7 : 25 함평천지클럽&함평희망클럽 김정수 / 김희수 2026.02.28(토) 15:45 4코트 6번","includesClub":false},{"date":"2026.02.28(토)","time":"16:00","court":"7코트","matchNo":"7번","title":"개인전 남복 50대B그룹 통합급수 - 풀리그","status":"경기종료","firstTeam":"함평천지클럽&함평희망클럽 (김정수 / 김희수)","secondTeam":"함평해월클럽 (오상열 / 이재두)","score":"25 : 22","text":"경기종료 개인전 남복 50대B그룹 통합급수 - 풀리그 함평천지클럽&함평희망클럽 김정수 / 김희수 25 : 22 함평해월클럽 오상열 / 이재두 2026.02.28(토) 16:00 7코트 7번","includesClub":false},{"date":"2026.02.28(토)","time":"16:00","court":"6코트","matchNo":"7번","title":"개인전 남복 50대B그룹 통합급수 - 풀리그","status":"경기종료","firstTeam":"함평함평클럽 (김남현 / 신고균)","secondTeam":"함평희망클럽 (이재국 / 정동섭)","score":"25 : 8","text":"경기종료 개인전 남복 50대B그룹 통합급수 - 풀리그 함평함평클럽 김남현 / 신고균 25 : 8 함평희망클럽 이재국 / 정동섭 2026.02.28(토) 16:00 6코트 7번","includesClub":false},{"date":"2026.02.28(토)","time":"16:15","court":"8코트","matchNo":"8번","title":"개인전 남복 50대B그룹 통합급수 - 풀리그","status":"경기종료","firstTeam":"함평해월클럽 (박내주 / 김희옥)","secondTeam":"함평천지클럽&함평희망클럽 (김정수 / 김희수)","score":"25 : 18","text":"경기종료 개인전 남복 50대B그룹 통합급수 - 풀리그 함평해월클럽 박내주 / 김희옥 25 : 18 함평천지클럽&함평희망클럽 김정수 / 김희수 2026.02.28(토) 16:15 8코트 8번","includesClub":false},{"date":"2026.02.28(토)","time":"16:15","court":"7코트","matchNo":"8번","title":"개인전 남복 50대B그룹 통합급수 - 풀리그","status":"경기종료","firstTeam":"함평해월클럽 (오상열 / 이재두)","secondTeam":"함평함평클럽 (김남현 / 신고균)","score":"25 : 13","text":"경기종료 개인전 남복 50대B그룹 통합급수 - 풀리그 함평해월클럽 오상열 / 이재두 25 : 13 함평함평클럽 김남현 / 신고균 2026.02.28(토) 16:15 7코트 8번","includesClub":false},{"date":"2026.02.28(토)","time":"16:30","court":"8코트","matchNo":"9번","title":"개인전 남복 50대B그룹 통합급수 - 풀리그","status":"경기종료","firstTeam":"함평천지클럽&함평희망클럽 (김정수 / 김희수)","secondTeam":"함평함평클럽 (김남현 / 신고균)","score":"22 : 25","text":"경기종료 개인전 남복 50대B그룹 통합급수 - 풀리그 함평천지클럽&함평희망클럽 김정수 / 김희수 22 : 25 함평함평클럽 김남현 / 신고균 2026.02.28(토) 16:30 8코트 9번","includesClub":false},{"date":"2026.02.28(토)","time":"16:30","court":"7코트","matchNo":"9번","title":"개인전 남복 50대B그룹 통합급수 - 풀리그","status":"경기종료","firstTeam":"함평해월클럽 (박내주 / 김희옥)","secondTeam":"함평희망클럽 (이재국 / 정동섭)","score":"25 : 8","text":"경기종료 개인전 남복 50대B그룹 통합급수 - 풀리그 함평해월클럽 박내주 / 김희옥 25 : 8 함평희망클럽 이재국 / 정동섭 2026.02.28(토) 16:30 7코트 9번","includesClub":false}],"sourceUrl":"https://sfa.bkplay.kr/tournament/qualifierMatch?tnmtId=3734&playingCategoryId=88524&groupId=109298"},{"drawId":"88526-109296","tournamentId":"3734","tournamentName":"2026년 함평군 협회장배 배드민턴 대회","tournamentStatus":"종료","tournamentStartDate":"2026.02.28","tournamentEndDate":"2026.02.28","tournamentVenue":"대동문화체육센터","category":{"event":"남복","age":"60대","level":"통합급수","teamCount":3,"playingCategoryId":"88526","title":"남복 60대 통합급수","sourceUrl":"https://sfa.bkplay.kr/tournament/qualifierMatch?tnmtId=3734&playingCategoryId=88526&groupId=109296"},"groupName":"1조","groupId":"109296","matchDate":"02월28일(토)","venue":"대동문화체육센터","standings":[{"rank":1,"teamName":"함평해월클럽","players":["김성진","이명국"],"wins":2,"losses":0,"game":{"scored":2,"conceded":0,"diff":2},"point":{"scored":50,"conceded":37,"diff":13},"includesClub":false,"isCombinedClub":false},{"rank":2,"teamName":"함평해월클럽","players":["이상륜","전순호"],"wins":1,"losses":1,"game":{"scored":1,"conceded":1,"diff":0},"point":{"scored":39,"conceded":43,"diff":-4},"includesClub":false,"isCombinedClub":false},{"rank":3,"teamName":"함평학다리클럽","players":["양시정","배대숙"],"wins":0,"losses":2,"game":{"scored":0,"conceded":2,"diff":-2},"point":{"scored":41,"conceded":50,"diff":-9},"includesClub":false,"isCombinedClub":false}],"matches":[{"date":"2026.02.28(토)","time":"15:30","court":"7코트","matchNo":"5번","title":"개인전 남복 60대 통합급수 - 풀리그","status":"경기종료","firstTeam":"함평해월클럽 (김성진 / 이명국)","secondTeam":"함평학다리클럽 (양시정 / 배대숙)","score":"25 : 23","text":"경기종료 개인전 남복 60대 통합급수 - 풀리그 함평해월클럽 김성진 / 이명국 25 : 23 함평학다리클럽 양시정 / 배대숙 2026.02.28(토) 15:30 7코트 5번","includesClub":false},{"date":"2026.02.28(토)","time":"16:15","court":"4코트","matchNo":"8번","title":"개인전 남복 60대 통합급수 - 풀리그","status":"경기종료","firstTeam":"함평해월클럽 (이상륜 / 전순호)","secondTeam":"함평해월클럽 (김성진 / 이명국)","score":"14 : 25","text":"경기종료 개인전 남복 60대 통합급수 - 풀리그 함평해월클럽 이상륜 / 전순호 14 : 25 함평해월클럽 김성진 / 이명국 2026.02.28(토) 16:15 4코트 8번","includesClub":false},{"date":"2026.02.28(토)","time":"16:30","court":"5코트","matchNo":"9번","title":"개인전 남복 60대 통합급수 - 풀리그","status":"경기종료","firstTeam":"함평학다리클럽 (양시정 / 배대숙)","secondTeam":"함평해월클럽 (이상륜 / 전순호)","score":"18 : 25","text":"경기종료 개인전 남복 60대 통합급수 - 풀리그 함평학다리클럽 양시정 / 배대숙 18 : 25 함평해월클럽 이상륜 / 전순호 2026.02.28(토) 16:30 5코트 9번","includesClub":false}],"sourceUrl":"https://sfa.bkplay.kr/tournament/qualifierMatch?tnmtId=3734&playingCategoryId=88526&groupId=109296"},{"drawId":"88515-109289","tournamentId":"3734","tournamentName":"2026년 함평군 협회장배 배드민턴 대회","tournamentStatus":"종료","tournamentStartDate":"2026.02.28","tournamentEndDate":"2026.02.28","tournamentVenue":"대동문화체육센터","category":{"event":"여복","age":"40미만A그룹","level":"통합급수","teamCount":5,"playingCategoryId":"88515","title":"여복 40미만A그룹 통합급수","sourceUrl":"https://sfa.bkplay.kr/tournament/qualifierMatch?tnmtId=3734&playingCategoryId=88515&groupId=109289"},"groupName":"1조","groupId":"109289","matchDate":"02월28일(토)","venue":"대동문화체육센터","standings":[{"rank":1,"teamName":"함평학다리클럽","players":["정선주","최지혜"],"wins":4,"losses":0,"game":{"scored":4,"conceded":0,"diff":4},"point":{"scored":100,"conceded":55,"diff":45},"includesClub":false,"isCombinedClub":false},{"rank":2,"teamName":"함평천지클럽&함평학다리클럽","players":["정경란","임아라"],"wins":2,"losses":2,"game":{"scored":2,"conceded":2,"diff":0},"point":{"scored":85,"conceded":80,"diff":5},"includesClub":false,"isCombinedClub":false},{"rank":3,"teamName":"함평함평클럽","players":["이은창","황점숙"],"wins":2,"losses":2,"game":{"scored":2,"conceded":2,"diff":0},"point":{"scored":82,"conceded":84,"diff":-2},"includesClub":false,"isCombinedClub":false},{"rank":4,"teamName":"함평학다리클럽","players":["이공심","김민순"],"wins":2,"losses":2,"game":{"scored":2,"conceded":2,"diff":0},"point":{"scored":80,"conceded":88,"diff":-8},"includesClub":false,"isCombinedClub":false},{"rank":5,"teamName":"함평함평클럽","players":["박계임","이수현"],"wins":0,"losses":4,"game":{"scored":0,"conceded":4,"diff":-4},"point":{"scored":60,"conceded":100,"diff":-40},"includesClub":false,"isCombinedClub":false}],"matches":[{"date":"2026.02.28(토)","time":"15:15","court":"3코트","matchNo":"4번","title":"개인전 여복 40미만A그룹 통합급수 - 풀리그","status":"경기종료","firstTeam":"함평학다리클럽 (정선주 / 최지혜)","secondTeam":"함평함평클럽 (이은창 / 황점숙)","score":"25 : 11","text":"경기종료 개인전 여복 40미만A그룹 통합급수 - 풀리그 함평학다리클럽 정선주 / 최지혜 25 : 11 함평함평클럽 이은창 / 황점숙 2026.02.28(토) 15:15 3코트 4번","includesClub":false},{"date":"2026.02.28(토)","time":"15:15","court":"4코트","matchNo":"4번","title":"개인전 여복 40미만A그룹 통합급수 - 풀리그","status":"경기종료","firstTeam":"함평학다리클럽 (이공심 / 김민순)","secondTeam":"함평함평클럽 (박계임 / 이수현)","score":"25 : 17","text":"경기종료 개인전 여복 40미만A그룹 통합급수 - 풀리그 함평학다리클럽 이공심 / 김민순 25 : 17 함평함평클럽 박계임 / 이수현 2026.02.28(토) 15:15 4코트 4번","includesClub":false},{"date":"2026.02.28(토)","time":"15:30","court":"3코트","matchNo":"5번","title":"개인전 여복 40미만A그룹 통합급수 - 풀리그","status":"경기종료","firstTeam":"함평천지클럽&함평학다리클럽 (정경란 / 임아라)","secondTeam":"함평함평클럽 (박계임 / 이수현)","score":"25 : 15","text":"경기종료 개인전 여복 40미만A그룹 통합급수 - 풀리그 함평천지클럽&함평학다리클럽 정경란 / 임아라 25 : 15 함평함평클럽 박계임 / 이수현 2026.02.28(토) 15:30 3코트 5번","includesClub":false},{"date":"2026.02.28(토)","time":"15:30","court":"4코트","matchNo":"5번","title":"개인전 여복 40미만A그룹 통합급수 - 풀리그","status":"경기종료","firstTeam":"함평학다리클럽 (정선주 / 최지혜)","secondTeam":"함평학다리클럽 (이공심 / 김민순)","score":"25 : 15","text":"경기종료 개인전 여복 40미만A그룹 통합급수 - 풀리그 함평학다리클럽 정선주 / 최지혜 25 : 15 함평학다리클럽 이공심 / 김민순 2026.02.28(토) 15:30 4코트 5번","includesClub":false},{"date":"2026.02.28(토)","time":"16:00","court":"3코트","matchNo":"7번","title":"개인전 여복 40미만A그룹 통합급수 - 풀리그","status":"경기종료","firstTeam":"함평함평클럽 (이은창 / 황점숙)","secondTeam":"함평천지클럽&함평학다리클럽 (정경란 / 임아라)","score":"25 : 17","text":"경기종료 개인전 여복 40미만A그룹 통합급수 - 풀리그 함평함평클럽 이은창 / 황점숙 25 : 17 함평천지클럽&함평학다리클럽 정경란 / 임아라 2026.02.28(토) 16:00 3코트 7번","includesClub":false},{"date":"2026.02.28(토)","time":"16:00","court":"2코트","matchNo":"7번","title":"개인전 여복 40미만A그룹 통합급수 - 풀리그","status":"경기종료","firstTeam":"함평함평클럽 (박계임 / 이수현)","secondTeam":"함평학다리클럽 (정선주 / 최지혜)","score":"11 : 25","text":"경기종료 개인전 여복 40미만A그룹 통합급수 - 풀리그 함평함평클럽 박계임 / 이수현 11 : 25 함평학다리클럽 정선주 / 최지혜 2026.02.28(토) 16:00 2코트 7번","includesClub":false},{"date":"2026.02.28(토)","time":"16:15","court":"3코트","matchNo":"8번","title":"개인전 여복 40미만A그룹 통합급수 - 풀리그","status":"경기종료","firstTeam":"함평함평클럽 (박계임 / 이수현)","secondTeam":"함평함평클럽 (이은창 / 황점숙)","score":"17 : 25","text":"경기종료 개인전 여복 40미만A그룹 통합급수 - 풀리그 함평함평클럽 박계임 / 이수현 17 : 25 함평함평클럽 이은창 / 황점숙 2026.02.28(토) 16:15 3코트 8번","includesClub":false},{"date":"2026.02.28(토)","time":"16:15","court":"2코트","matchNo":"8번","title":"개인전 여복 40미만A그룹 통합급수 - 풀리그","status":"경기종료","firstTeam":"함평학다리클럽 (이공심 / 김민순)","secondTeam":"함평천지클럽&함평학다리클럽 (정경란 / 임아라)","score":"15 : 25","text":"경기종료 개인전 여복 40미만A그룹 통합급수 - 풀리그 함평학다리클럽 이공심 / 김민순 15 : 25 함평천지클럽&함평학다리클럽 정경란 / 임아라 2026.02.28(토) 16:15 2코트 8번","includesClub":false},{"date":"2026.02.28(토)","time":"16:30","court":"3코트","matchNo":"9번","title":"개인전 여복 40미만A그룹 통합급수 - 풀리그","status":"경기종료","firstTeam":"함평천지클럽&함평학다리클럽 (정경란 / 임아라)","secondTeam":"함평학다리클럽 (정선주 / 최지혜)","score":"18 : 25","text":"경기종료 개인전 여복 40미만A그룹 통합급수 - 풀리그 함평천지클럽&함평학다리클럽 정경란 / 임아라 18 : 25 함평학다리클럽 정선주 / 최지혜 2026.02.28(토) 16:30 3코트 9번","includesClub":false},{"date":"2026.02.28(토)","time":"16:30","court":"4코트","matchNo":"9번","title":"개인전 여복 40미만A그룹 통합급수 - 풀리그","status":"경기종료","firstTeam":"함평함평클럽 (이은창 / 황점숙)","secondTeam":"함평학다리클럽 (이공심 / 김민순)","score":"21 : 25","text":"경기종료 개인전 여복 40미만A그룹 통합급수 - 풀리그 함평함평클럽 이은창 / 황점숙 21 : 25 함평학다리클럽 이공심 / 김민순 2026.02.28(토) 16:30 4코트 9번","includesClub":false}],"sourceUrl":"https://sfa.bkplay.kr/tournament/qualifierMatch?tnmtId=3734&playingCategoryId=88515&groupId=109289"},{"drawId":"88521-109290","tournamentId":"3734","tournamentName":"2026년 함평군 협회장배 배드민턴 대회","tournamentStatus":"종료","tournamentStartDate":"2026.02.28","tournamentEndDate":"2026.02.28","tournamentVenue":"대동문화체육센터","category":{"event":"여복","age":"40미만B그룹","level":"통합급수","teamCount":3,"playingCategoryId":"88521","title":"여복 40미만B그룹 통합급수","sourceUrl":"https://sfa.bkplay.kr/tournament/qualifierMatch?tnmtId=3734&playingCategoryId=88521&groupId=109290"},"groupName":"1조","groupId":"109290","matchDate":"02월28일(토)","venue":"대동문화체육센터","standings":[{"rank":1,"teamName":"함평함평클럽","players":["이효진","임지현"],"wins":2,"losses":0,"game":{"scored":2,"conceded":0,"diff":2},"point":{"scored":50,"conceded":34,"diff":16},"includesClub":false,"isCombinedClub":false},{"rank":2,"teamName":"함평함평클럽","players":["박은희","박경미"],"wins":1,"losses":1,"game":{"scored":1,"conceded":1,"diff":0},"point":{"scored":45,"conceded":42,"diff":3},"includesClub":false,"isCombinedClub":false},{"rank":3,"teamName":"함평희망클럽","players":["윤선미","서예지"],"wins":0,"losses":2,"game":{"scored":0,"conceded":2,"diff":-2},"point":{"scored":31,"conceded":50,"diff":-19},"includesClub":false,"isCombinedClub":false}],"matches":[{"date":"2026.02.28(토)","time":"15:15","court":"8코트","matchNo":"4번","title":"개인전 여복 40미만B그룹 통합급수 - 풀리그","status":"경기종료","firstTeam":"함평함평클럽 (박은희 / 박경미)","secondTeam":"함평희망클럽 (윤선미 / 서예지)","score":"25 : 17","text":"경기종료 개인전 여복 40미만B그룹 통합급수 - 풀리그 함평함평클럽 박은희 / 박경미 25 : 17 함평희망클럽 윤선미 / 서예지 2026.02.28(토) 15:15 8코트 4번","includesClub":false},{"date":"2026.02.28(토)","time":"15:45","court":"3코트","matchNo":"6번","title":"개인전 여복 40미만B그룹 통합급수 - 풀리그","status":"경기종료","firstTeam":"함평희망클럽 (윤선미 / 서예지)","secondTeam":"함평함평클럽 (이효진 / 임지현)","score":"14 : 25","text":"경기종료 개인전 여복 40미만B그룹 통합급수 - 풀리그 함평희망클럽 윤선미 / 서예지 14 : 25 함평함평클럽 이효진 / 임지현 2026.02.28(토) 15:45 3코트 6번","includesClub":false},{"date":"2026.02.28(토)","time":"16:00","court":"4코트","matchNo":"7번","title":"개인전 여복 40미만B그룹 통합급수 - 풀리그","status":"경기종료","firstTeam":"함평함평클럽 (이효진 / 임지현)","secondTeam":"함평함평클럽 (박은희 / 박경미)","score":"25 : 20","text":"경기종료 개인전 여복 40미만B그룹 통합급수 - 풀리그 함평함평클럽 이효진 / 임지현 25 : 20 함평함평클럽 박은희 / 박경미 2026.02.28(토) 16:00 4코트 7번","includesClub":false}],"sourceUrl":"https://sfa.bkplay.kr/tournament/qualifierMatch?tnmtId=3734&playingCategoryId=88521&groupId=109290"},{"drawId":"88525-109291","tournamentId":"3734","tournamentName":"2026년 함평군 협회장배 배드민턴 대회","tournamentStatus":"종료","tournamentStartDate":"2026.02.28","tournamentEndDate":"2026.02.28","tournamentVenue":"대동문화체육센터","category":{"event":"여복","age":"50대B그룹","level":"통합급수","teamCount":4,"playingCategoryId":"88525","title":"여복 50대B그룹 통합급수","sourceUrl":"https://sfa.bkplay.kr/tournament/qualifierMatch?tnmtId=3734&playingCategoryId=88525&groupId=109291"},"groupName":"1조","groupId":"109291","matchDate":"02월28일(토)","venue":"대동문화체육센터","standings":[{"rank":1,"teamName":"함평희망클럽","players":["이지혜","장미경"],"wins":3,"losses":0,"game":{"scored":3,"conceded":0,"diff":3},"point":{"scored":75,"conceded":61,"diff":14},"includesClub":false,"isCombinedClub":false},{"rank":2,"teamName":"함평천지클럽","players":["박현미","김애숙"],"wins":2,"losses":1,"game":{"scored":2,"conceded":1,"diff":1},"point":{"scored":70,"conceded":52,"diff":18},"includesClub":false,"isCombinedClub":false},{"rank":3,"teamName":"함평해월클럽","players":["주영남","주민아"],"wins":1,"losses":2,"game":{"scored":1,"conceded":2,"diff":-1},"point":{"scored":52,"conceded":68,"diff":-16},"includesClub":false,"isCombinedClub":false},{"rank":4,"teamName":"함평해월클럽&함평손불클럽","players":["이순애","최순"],"wins":0,"losses":3,"game":{"scored":0,"conceded":3,"diff":-3},"point":{"scored":59,"conceded":75,"diff":-16},"includesClub":false,"isCombinedClub":false}],"matches":[{"date":"2026.02.28(토)","time":"15:30","court":"8코트","matchNo":"5번","title":"개인전 여복 50대B그룹 통합급수 - 풀리그","status":"경기종료","firstTeam":"함평해월클럽 (주영남 / 주민아)","secondTeam":"함평희망클럽 (이지혜 / 장미경)","score":"20 : 25","text":"경기종료 개인전 여복 50대B그룹 통합급수 - 풀리그 함평해월클럽 주영남 / 주민아 20 : 25 함평희망클럽 이지혜 / 장미경 2026.02.28(토) 15:30 8코트 5번","includesClub":false},{"date":"2026.02.28(토)","time":"15:45","court":"9코트","matchNo":"6번","title":"개인전 여복 50대B그룹 통합급수 - 풀리그","status":"경기종료","firstTeam":"함평희망클럽 (이지혜 / 장미경)","secondTeam":"함평천지클럽 (박현미 / 김애숙)","score":"25 : 20","text":"경기종료 개인전 여복 50대B그룹 통합급수 - 풀리그 함평희망클럽 이지혜 / 장미경 25 : 20 함평천지클럽 박현미 / 김애숙 2026.02.28(토) 15:45 9코트 6번","includesClub":false},{"date":"2026.02.28(토)","time":"15:45","court":"8코트","matchNo":"6번","title":"개인전 여복 50대B그룹 통합급수 - 풀리그","status":"경기종료","firstTeam":"함평해월클럽 (주영남 / 주민아)","secondTeam":"함평해월클럽&함평손불클럽 (이순애 / 최순)","score":"25 : 18","text":"경기종료 개인전 여복 50대B그룹 통합급수 - 풀리그 함평해월클럽 주영남 / 주민아 25 : 18 함평해월클럽&함평손불클럽 이순애 / 최순 2026.02.28(토) 15:45 8코트 6번","includesClub":false},{"date":"2026.02.28(토)","time":"16:00","court":"8코트","matchNo":"7번","title":"개인전 여복 50대B그룹 통합급수 - 풀리그","status":"경기종료","firstTeam":"함평천지클럽 (박현미 / 김애숙)","secondTeam":"함평해월클럽&함평손불클럽 (이순애 / 최순)","score":"25 : 20","text":"경기종료 개인전 여복 50대B그룹 통합급수 - 풀리그 함평천지클럽 박현미 / 김애숙 25 : 20 함평해월클럽&함평손불클럽 이순애 / 최순 2026.02.28(토) 16:00 8코트 7번","includesClub":false},{"date":"2026.02.28(토)","time":"16:30","court":"2코트","matchNo":"9번","title":"개인전 여복 50대B그룹 통합급수 - 풀리그","status":"경기종료","firstTeam":"함평천지클럽 (박현미 / 김애숙)","secondTeam":"함평해월클럽 (주영남 / 주민아)","score":"25 : 7","text":"경기종료 개인전 여복 50대B그룹 통합급수 - 풀리그 함평천지클럽 박현미 / 김애숙 25 : 7 함평해월클럽 주영남 / 주민아 2026.02.28(토) 16:30 2코트 9번","includesClub":false},{"date":"2026.02.28(토)","time":"16:30","court":"1코트","matchNo":"9번","title":"개인전 여복 50대B그룹 통합급수 - 풀리그","status":"경기종료","firstTeam":"함평희망클럽 (이지혜 / 장미경)","secondTeam":"함평해월클럽&함평손불클럽 (이순애 / 최순)","score":"25 : 21","text":"경기종료 개인전 여복 50대B그룹 통합급수 - 풀리그 함평희망클럽 이지혜 / 장미경 25 : 21 함평해월클럽&함평손불클럽 이순애 / 최순 2026.02.28(토) 16:30 1코트 9번","includesClub":false}],"sourceUrl":"https://sfa.bkplay.kr/tournament/qualifierMatch?tnmtId=3734&playingCategoryId=88525&groupId=109291"},{"drawId":"88528-109292","tournamentId":"3734","tournamentName":"2026년 함평군 협회장배 배드민턴 대회","tournamentStatus":"종료","tournamentStartDate":"2026.02.28","tournamentEndDate":"2026.02.28","tournamentVenue":"대동문화체육센터","category":{"event":"혼복","age":"45미만","level":"통합급수","teamCount":4,"playingCategoryId":"88528","title":"혼복 45미만 통합급수","sourceUrl":"https://sfa.bkplay.kr/tournament/qualifierMatch?tnmtId=3734&playingCategoryId=88528&groupId=109292"},"groupName":"1조","groupId":"109292","matchDate":"02월28일(토)","venue":"대동문화체육센터","standings":[{"rank":1,"teamName":"함평함평클럽&함평학다리클럽","players":["임영인","정선주"],"wins":3,"losses":0,"game":{"scored":3,"conceded":0,"diff":3},"point":{"scored":75,"conceded":38,"diff":37},"includesClub":false,"isCombinedClub":false},{"rank":2,"teamName":"함평희망클럽","players":["이태성","서예지"],"wins":2,"losses":1,"game":{"scored":2,"conceded":1,"diff":1},"point":{"scored":60,"conceded":58,"diff":2},"includesClub":false,"isCombinedClub":false},{"rank":3,"teamName":"함평함평클럽","players":["문민후","임지현"],"wins":1,"losses":2,"game":{"scored":1,"conceded":2,"diff":-1},"point":{"scored":68,"conceded":63,"diff":5},"includesClub":false,"isCombinedClub":false},{"rank":4,"teamName":"함평천지클럽","players":["김용환","유혜진"],"wins":0,"losses":3,"game":{"scored":0,"conceded":3,"diff":-3},"point":{"scored":31,"conceded":75,"diff":-44},"includesClub":false,"isCombinedClub":false}],"matches":[{"date":"2026.02.28(토)","time":"13:00","court":"4코트","matchNo":"1번","title":"개인전 혼복 45미만 통합급수 - 풀리그","status":"경기종료","firstTeam":"함평함평클럽 (문민후 / 임지현)","secondTeam":"함평천지클럽 (김용환 / 유혜진)","score":"25 : 13","text":"경기종료 개인전 혼복 45미만 통합급수 - 풀리그 함평함평클럽 문민후 / 임지현 25 : 13 함평천지클럽 김용환 / 유혜진 2026.02.28(토) 13:00 4코트 1번","includesClub":false},{"date":"2026.02.28(토)","time":"13:00","court":"3코트","matchNo":"1번","title":"개인전 혼복 45미만 통합급수 - 풀리그","status":"경기종료","firstTeam":"함평함평클럽&함평학다리클럽 (임영인 / 정선주)","secondTeam":"함평희망클럽 (이태성 / 서예지)","score":"25 : 10","text":"경기종료 개인전 혼복 45미만 통합급수 - 풀리그 함평함평클럽&함평학다리클럽 임영인 / 정선주 25 : 10 함평희망클럽 이태성 / 서예지 2026.02.28(토) 13:00 3코트 1번","includesClub":false},{"date":"2026.02.28(토)","time":"13:15","court":"4코트","matchNo":"2번","title":"개인전 혼복 45미만 통합급수 - 풀리그","status":"경기종료","firstTeam":"함평천지클럽 (김용환 / 유혜진)","secondTeam":"함평함평클럽&함평학다리클럽 (임영인 / 정선주)","score":"8 : 25","text":"경기종료 개인전 혼복 45미만 통합급수 - 풀리그 함평천지클럽 김용환 / 유혜진 8 : 25 함평함평클럽&함평학다리클럽 임영인 / 정선주 2026.02.28(토) 13:15 4코트 2번","includesClub":false},{"date":"2026.02.28(토)","time":"13:15","court":"3코트","matchNo":"2번","title":"개인전 혼복 45미만 통합급수 - 풀리그","status":"경기종료","firstTeam":"함평함평클럽 (문민후 / 임지현)","secondTeam":"함평희망클럽 (이태성 / 서예지)","score":"23 : 25","text":"경기종료 개인전 혼복 45미만 통합급수 - 풀리그 함평함평클럽 문민후 / 임지현 23 : 25 함평희망클럽 이태성 / 서예지 2026.02.28(토) 13:15 3코트 2번","includesClub":false},{"date":"2026.02.28(토)","time":"15:00","court":"4코트","matchNo":"3번","title":"개인전 혼복 45미만 통합급수 - 풀리그","status":"경기종료","firstTeam":"함평함평클럽&함평학다리클럽 (임영인 / 정선주)","secondTeam":"함평함평클럽 (문민후 / 임지현)","score":"25 : 20","text":"경기종료 개인전 혼복 45미만 통합급수 - 풀리그 함평함평클럽&함평학다리클럽 임영인 / 정선주 25 : 20 함평함평클럽 문민후 / 임지현 2026.02.28(토) 15:00 4코트 3번","includesClub":false},{"date":"2026.02.28(토)","time":"15:00","court":"3코트","matchNo":"3번","title":"개인전 혼복 45미만 통합급수 - 풀리그","status":"경기종료","firstTeam":"함평천지클럽 (김용환 / 유혜진)","secondTeam":"함평희망클럽 (이태성 / 서예지)","score":"10 : 25","text":"경기종료 개인전 혼복 45미만 통합급수 - 풀리그 함평천지클럽 김용환 / 유혜진 10 : 25 함평희망클럽 이태성 / 서예지 2026.02.28(토) 15:00 3코트 3번","includesClub":false}],"sourceUrl":"https://sfa.bkplay.kr/tournament/qualifierMatch?tnmtId=3734&playingCategoryId=88528&groupId=109292"},{"drawId":"88841-109293","tournamentId":"3734","tournamentName":"2026년 함평군 협회장배 배드민턴 대회","tournamentStatus":"종료","tournamentStartDate":"2026.02.28","tournamentEndDate":"2026.02.28","tournamentVenue":"대동문화체육센터","category":{"event":"혼복","age":"45이상 1조","level":"통합급수","teamCount":4,"playingCategoryId":"88841","title":"혼복 45이상 1조 통합급수","sourceUrl":"https://sfa.bkplay.kr/tournament/qualifierMatch?tnmtId=3734&playingCategoryId=88841&groupId=109293"},"groupName":"1조","groupId":"109293","matchDate":"02월28일(토)","venue":"대동문화체육센터","standings":[{"rank":1,"teamName":"함평천지클럽","players":["신동선","정경란"],"wins":3,"losses":0,"game":{"scored":3,"conceded":0,"diff":3},"point":{"scored":75,"conceded":50,"diff":25},"includesClub":false,"isCombinedClub":false},{"rank":2,"teamName":"함평학다리클럽","players":["이영재","최지혜"],"wins":2,"losses":1,"game":{"scored":2,"conceded":1,"diff":1},"point":{"scored":72,"conceded":61,"diff":11},"includesClub":false,"isCombinedClub":false},{"rank":3,"teamName":"함평희망클럽&함평함평클럽","players":["윤광현","박계임"],"wins":1,"losses":2,"game":{"scored":1,"conceded":2,"diff":-1},"point":{"scored":67,"conceded":74,"diff":-7},"includesClub":false,"isCombinedClub":false},{"rank":4,"teamName":"함평학다리클럽","players":["이형주","이공심"],"wins":0,"losses":3,"game":{"scored":0,"conceded":3,"diff":-3},"point":{"scored":46,"conceded":75,"diff":-29},"includesClub":false,"isCombinedClub":false}],"matches":[{"date":"2026.02.28(토)","time":"13:00","court":"6코트","matchNo":"1번","title":"개인전 혼복 45이상 1조 통합급수 - 풀리그","status":"경기종료","firstTeam":"함평학다리클럽 (이형주 / 이공심)","secondTeam":"함평학다리클럽 (이영재 / 최지혜)","score":"12 : 25","text":"경기종료 개인전 혼복 45이상 1조 통합급수 - 풀리그 함평학다리클럽 이형주 / 이공심 12 : 25 함평학다리클럽 이영재 / 최지혜 2026.02.28(토) 13:00 6코트 1번","includesClub":false},{"date":"2026.02.28(토)","time":"13:00","court":"5코트","matchNo":"1번","title":"개인전 혼복 45이상 1조 통합급수 - 풀리그","status":"경기종료","firstTeam":"함평천지클럽 (신동선 / 정경란)","secondTeam":"함평희망클럽&함평함평클럽 (윤광현 / 박계임)","score":"25 : 18","text":"경기종료 개인전 혼복 45이상 1조 통합급수 - 풀리그 함평천지클럽 신동선 / 정경란 25 : 18 함평희망클럽&함평함평클럽 윤광현 / 박계임 2026.02.28(토) 13:00 5코트 1번","includesClub":false},{"date":"2026.02.28(토)","time":"13:15","court":"6코트","matchNo":"2번","title":"개인전 혼복 45이상 1조 통합급수 - 풀리그","status":"경기종료","firstTeam":"함평학다리클럽 (이영재 / 최지혜)","secondTeam":"함평천지클럽 (신동선 / 정경란)","score":"22 : 25","text":"경기종료 개인전 혼복 45이상 1조 통합급수 - 풀리그 함평학다리클럽 이영재 / 최지혜 22 : 25 함평천지클럽 신동선 / 정경란 2026.02.28(토) 13:15 6코트 2번","includesClub":false},{"date":"2026.02.28(토)","time":"13:15","court":"5코트","matchNo":"2번","title":"개인전 혼복 45이상 1조 통합급수 - 풀리그","status":"경기종료","firstTeam":"함평학다리클럽 (이형주 / 이공심)","secondTeam":"함평희망클럽&함평함평클럽 (윤광현 / 박계임)","score":"24 : 25","text":"경기종료 개인전 혼복 45이상 1조 통합급수 - 풀리그 함평학다리클럽 이형주 / 이공심 24 : 25 함평희망클럽&함평함평클럽 윤광현 / 박계임 2026.02.28(토) 13:15 5코트 2번","includesClub":false},{"date":"2026.02.28(토)","time":"15:00","court":"6코트","matchNo":"3번","title":"개인전 혼복 45이상 1조 통합급수 - 풀리그","status":"경기종료","firstTeam":"함평천지클럽 (신동선 / 정경란)","secondTeam":"함평학다리클럽 (이형주 / 이공심)","score":"25 : 10","text":"경기종료 개인전 혼복 45이상 1조 통합급수 - 풀리그 함평천지클럽 신동선 / 정경란 25 : 10 함평학다리클럽 이형주 / 이공심 2026.02.28(토) 15:00 6코트 3번","includesClub":false},{"date":"2026.02.28(토)","time":"15:00","court":"5코트","matchNo":"3번","title":"개인전 혼복 45이상 1조 통합급수 - 풀리그","status":"경기종료","firstTeam":"함평학다리클럽 (이영재 / 최지혜)","secondTeam":"함평희망클럽&함평함평클럽 (윤광현 / 박계임)","score":"25 : 24","text":"경기종료 개인전 혼복 45이상 1조 통합급수 - 풀리그 함평학다리클럽 이영재 / 최지혜 25 : 24 함평희망클럽&함평함평클럽 윤광현 / 박계임 2026.02.28(토) 15:00 5코트 3번","includesClub":false}],"sourceUrl":"https://sfa.bkplay.kr/tournament/qualifierMatch?tnmtId=3734&playingCategoryId=88841&groupId=109293"},{"drawId":"88842-109294","tournamentId":"3734","tournamentName":"2026년 함평군 협회장배 배드민턴 대회","tournamentStatus":"종료","tournamentStartDate":"2026.02.28","tournamentEndDate":"2026.02.28","tournamentVenue":"대동문화체육센터","category":{"event":"혼복","age":"45이상 2조","level":"통합급수","teamCount":4,"playingCategoryId":"88842","title":"혼복 45이상 2조 통합급수","sourceUrl":"https://sfa.bkplay.kr/tournament/qualifierMatch?tnmtId=3734&playingCategoryId=88842&groupId=109294"},"groupName":"1조","groupId":"109294","matchDate":"02월28일(토)","venue":"대동문화체육센터","standings":[{"rank":1,"teamName":"함평천지클럽&함평함평클럽","players":["김제곤","황점숙"],"wins":3,"losses":0,"game":{"scored":2,"conceded":0,"diff":2},"point":{"scored":50,"conceded":31,"diff":19},"includesClub":false,"isCombinedClub":false},{"rank":2,"teamName":"함평손불클럽&함평학다리클럽","players":["김창석","임아라"],"wins":2,"losses":1,"game":{"scored":1,"conceded":1,"diff":0},"point":{"scored":36,"conceded":42,"diff":-6},"includesClub":false,"isCombinedClub":false},{"rank":3,"teamName":"함평해월클럽","players":["김희옥","주민아"],"wins":1,"losses":2,"game":{"scored":0,"conceded":2,"diff":-2},"point":{"scored":37,"conceded":50,"diff":-13},"includesClub":false,"isCombinedClub":false},{"rank":4,"teamName":"함평천지클럽","players":["김정수","김애숙"],"wins":0,"losses":3,"game":{"scored":0,"conceded":0,"diff":0},"point":{"scored":0,"conceded":0,"diff":0},"includesClub":false,"isCombinedClub":false}],"matches":[{"date":"2026.02.28(토)","time":"13:00","court":"8코트","matchNo":"1번","title":"개인전 혼복 45이상 2조 통합급수 - 풀리그","status":"경기종료","firstTeam":"함평천지클럽 (김정수 / 김애숙)","secondTeam":"함평해월클럽 (김희옥 / 주민아)","score":"0 : 0","text":"경기종료 개인전 혼복 45이상 2조 통합급수 - 풀리그 함평천지클럽 김정수 / 김애숙 0 : 0 함평해월클럽 김희옥 / 주민아 2026.02.28(토) 13:00 8코트 1번","includesClub":false},{"date":"2026.02.28(토)","time":"13:00","court":"7코트","matchNo":"1번","title":"개인전 혼복 45이상 2조 통합급수 - 풀리그","status":"경기종료","firstTeam":"함평천지클럽&함평함평클럽 (김제곤 / 황점숙)","secondTeam":"함평손불클럽&함평학다리클럽 (김창석 / 임아라)","score":"25 : 11","text":"경기종료 개인전 혼복 45이상 2조 통합급수 - 풀리그 함평천지클럽&함평함평클럽 김제곤 / 황점숙 25 : 11 함평손불클럽&함평학다리클럽 김창석 / 임아라 2026.02.28(토) 13:00 7코트 1번","includesClub":false},{"date":"2026.02.28(토)","time":"13:15","court":"8코트","matchNo":"2번","title":"개인전 혼복 45이상 2조 통합급수 - 풀리그","status":"경기종료","firstTeam":"함평해월클럽 (김희옥 / 주민아)","secondTeam":"함평천지클럽&함평함평클럽 (김제곤 / 황점숙)","score":"20 : 25","text":"경기종료 개인전 혼복 45이상 2조 통합급수 - 풀리그 함평해월클럽 김희옥 / 주민아 20 : 25 함평천지클럽&함평함평클럽 김제곤 / 황점숙 2026.02.28(토) 13:15 8코트 2번","includesClub":false},{"date":"2026.02.28(토)","time":"13:15","court":"7코트","matchNo":"2번","title":"개인전 혼복 45이상 2조 통합급수 - 풀리그","status":"경기종료","firstTeam":"함평천지클럽 (김정수 / 김애숙)","secondTeam":"함평손불클럽&함평학다리클럽 (김창석 / 임아라)","score":"0 : 0","text":"경기종료 개인전 혼복 45이상 2조 통합급수 - 풀리그 함평천지클럽 김정수 / 김애숙 0 : 0 함평손불클럽&함평학다리클럽 김창석 / 임아라 2026.02.28(토) 13:15 7코트 2번","includesClub":false},{"date":"2026.02.28(토)","time":"15:00","court":"8코트","matchNo":"3번","title":"개인전 혼복 45이상 2조 통합급수 - 풀리그","status":"경기종료","firstTeam":"함평천지클럽&함평함평클럽 (김제곤 / 황점숙)","secondTeam":"함평천지클럽 (김정수 / 김애숙)","score":"0 : 0","text":"경기종료 개인전 혼복 45이상 2조 통합급수 - 풀리그 함평천지클럽&함평함평클럽 김제곤 / 황점숙 0 : 0 함평천지클럽 김정수 / 김애숙 2026.02.28(토) 15:00 8코트 3번","includesClub":false},{"date":"2026.02.28(토)","time":"15:00","court":"7코트","matchNo":"3번","title":"개인전 혼복 45이상 2조 통합급수 - 풀리그","status":"경기종료","firstTeam":"함평해월클럽 (김희옥 / 주민아)","secondTeam":"함평손불클럽&함평학다리클럽 (김창석 / 임아라)","score":"17 : 25","text":"경기종료 개인전 혼복 45이상 2조 통합급수 - 풀리그 함평해월클럽 김희옥 / 주민아 17 : 25 함평손불클럽&함평학다리클럽 김창석 / 임아라 2026.02.28(토) 15:00 7코트 3번","includesClub":false}],"sourceUrl":"https://sfa.bkplay.kr/tournament/qualifierMatch?tnmtId=3734&playingCategoryId=88842&groupId=109294"},{"drawId":"88843-109295","tournamentId":"3734","tournamentName":"2026년 함평군 협회장배 배드민턴 대회","tournamentStatus":"종료","tournamentStartDate":"2026.02.28","tournamentEndDate":"2026.02.28","tournamentVenue":"대동문화체육센터","category":{"event":"혼복","age":"45이상 3조","level":"통합급수","teamCount":4,"playingCategoryId":"88843","title":"혼복 45이상 3조 통합급수","sourceUrl":"https://sfa.bkplay.kr/tournament/qualifierMatch?tnmtId=3734&playingCategoryId=88843&groupId=109295"},"groupName":"1조","groupId":"109295","matchDate":"02월28일(토)","venue":"대동문화체육센터","standings":[{"rank":1,"teamName":"함평해월클럽","players":["오상열","이순애"],"wins":2,"losses":1,"game":{"scored":2,"conceded":1,"diff":1},"point":{"scored":70,"conceded":66,"diff":4},"includesClub":false,"isCombinedClub":false},{"rank":2,"teamName":"함평해월클럽","players":["김홍배","주영남"],"wins":2,"losses":1,"game":{"scored":2,"conceded":1,"diff":1},"point":{"scored":69,"conceded":65,"diff":4},"includesClub":false,"isCombinedClub":false},{"rank":3,"teamName":"함평함평클럽","players":["신고균","임부덕"],"wins":1,"losses":2,"game":{"scored":1,"conceded":2,"diff":-1},"point":{"scored":63,"conceded":73,"diff":-10},"includesClub":false,"isCombinedClub":false},{"rank":4,"teamName":"함평해월클럽","players":["심만섭","정명순"],"wins":1,"losses":2,"game":{"scored":1,"conceded":2,"diff":-1},"point":{"scored":72,"conceded":70,"diff":2},"includesClub":false,"isCombinedClub":false}],"matches":[{"date":"2026.02.28(토)","time":"13:00","court":"10코트","matchNo":"1번","title":"개인전 혼복 45이상 3조 통합급수 - 풀리그","status":"경기종료","firstTeam":"함평해월클럽 (오상열 / 이순애)","secondTeam":"함평해월클럽 (김홍배 / 주영남)","score":"25 : 19","text":"경기종료 개인전 혼복 45이상 3조 통합급수 - 풀리그 함평해월클럽 오상열 / 이순애 25 : 19 함평해월클럽 김홍배 / 주영남 2026.02.28(토) 13:00 10코트 1번","includesClub":false},{"date":"2026.02.28(토)","time":"13:00","court":"9코트","matchNo":"1번","title":"개인전 혼복 45이상 3조 통합급수 - 풀리그","status":"경기종료","firstTeam":"함평함평클럽 (신고균 / 임부덕)","secondTeam":"함평해월클럽 (심만섭 / 정명순)","score":"25 : 23","text":"경기종료 개인전 혼복 45이상 3조 통합급수 - 풀리그 함평함평클럽 신고균 / 임부덕 25 : 23 함평해월클럽 심만섭 / 정명순 2026.02.28(토) 13:00 9코트 1번","includesClub":false},{"date":"2026.02.28(토)","time":"13:15","court":"10코트","matchNo":"2번","title":"개인전 혼복 45이상 3조 통합급수 - 풀리그","status":"경기종료","firstTeam":"함평해월클럽 (김홍배 / 주영남)","secondTeam":"함평함평클럽 (신고균 / 임부덕)","score":"25 : 16","text":"경기종료 개인전 혼복 45이상 3조 통합급수 - 풀리그 함평해월클럽 김홍배 / 주영남 25 : 16 함평함평클럽 신고균 / 임부덕 2026.02.28(토) 13:15 10코트 2번","includesClub":false},{"date":"2026.02.28(토)","time":"13:15","court":"9코트","matchNo":"2번","title":"개인전 혼복 45이상 3조 통합급수 - 풀리그","status":"경기종료","firstTeam":"함평해월클럽 (오상열 / 이순애)","secondTeam":"함평해월클럽 (심만섭 / 정명순)","score":"20 : 25","text":"경기종료 개인전 혼복 45이상 3조 통합급수 - 풀리그 함평해월클럽 오상열 / 이순애 20 : 25 함평해월클럽 심만섭 / 정명순 2026.02.28(토) 13:15 9코트 2번","includesClub":false},{"date":"2026.02.28(토)","time":"15:00","court":"10코트","matchNo":"3번","title":"개인전 혼복 45이상 3조 통합급수 - 풀리그","status":"경기종료","firstTeam":"함평함평클럽 (신고균 / 임부덕)","secondTeam":"함평해월클럽 (오상열 / 이순애)","score":"22 : 25","text":"경기종료 개인전 혼복 45이상 3조 통합급수 - 풀리그 함평함평클럽 신고균 / 임부덕 22 : 25 함평해월클럽 오상열 / 이순애 2026.02.28(토) 15:00 10코트 3번","includesClub":false},{"date":"2026.02.28(토)","time":"15:00","court":"9코트","matchNo":"3번","title":"개인전 혼복 45이상 3조 통합급수 - 풀리그","status":"경기종료","firstTeam":"함평해월클럽 (김홍배 / 주영남)","secondTeam":"함평해월클럽 (심만섭 / 정명순)","score":"25 : 24","text":"경기종료 개인전 혼복 45이상 3조 통합급수 - 풀리그 함평해월클럽 김홍배 / 주영남 25 : 24 함평해월클럽 심만섭 / 정명순 2026.02.28(토) 15:00 9코트 3번","includesClub":false}],"sourceUrl":"https://sfa.bkplay.kr/tournament/qualifierMatch?tnmtId=3734&playingCategoryId=88843&groupId=109295"}]}
