{"id":"3868","round":"1","name":"제22회 순천시생활체육대축전 및 제11회 클럽최강전 배드민턴대회(하이클리어 리그)","status":"종료","startDate":"2026.05.31","endDate":"2026.06.20","host":"순천시배드민턴협회","venue":"국민체육센터민(합60)","detailUrl":"https://sfa.bkplay.kr/tournament/detail.do?tnmtId=3868&tnmtRound=1","provinceOrgId":"15","provinceName":"전남","draws":[{"drawId":"98871-122295","tournamentId":"3868","tournamentName":"제22회 순천시생활체육대축전 및 제11회 클럽최강전 배드민턴대회(하이클리어 리그)","tournamentStatus":"종료","tournamentStartDate":"2026.05.31","tournamentEndDate":"2026.06.20","tournamentVenue":"국민체육센터민(합60)","category":{"event":"타입없음","age":"본선","level":"하이클리어","teamCount":3,"playingCategoryId":"98871","title":"타입없음 본선 하이클리어","sourceUrl":"https://sfa.bkplay.kr/tournament/qualifierMatch?tnmtId=3868&playingCategoryId=98871&groupId=122295"},"groupName":"1조","groupId":"122295","matchDate":"06월20일(토)","venue":"국민체육센터민(합60)","standings":[{"rank":1,"teamName":"승평클럽","players":[],"wins":2,"losses":0,"game":{"scored":8,"conceded":2,"diff":6},"point":{"scored":8,"conceded":2,"diff":6},"includesClub":false,"isCombinedClub":false},{"rank":2,"teamName":"부영클럽","players":[],"wins":1,"losses":1,"game":{"scored":3,"conceded":7,"diff":-4},"point":{"scored":3,"conceded":7,"diff":-4},"includesClub":false,"isCombinedClub":false},{"rank":3,"teamName":"왕운클럽","players":[],"wins":0,"losses":2,"game":{"scored":4,"conceded":6,"diff":-2},"point":{"scored":4,"conceded":6,"diff":-2},"includesClub":false,"isCombinedClub":false}],"matches":[{"date":"2026.06.20(토)","time":"08:00","court":"1코트","matchNo":"1번","title":"단체전 본선 하이클리어 - 풀리그","status":"경기종료","firstTeam":"부영클럽","secondTeam":"승평클럽","score":"0 : 5","text":"경기종료 단체전 본선 하이클리어 - 풀리그 부영클럽 0 : 5 승평클럽 2026.06.20(토) 08:00 1코트 1번 세부경기보기","includesClub":false},{"date":"2026.06.20(토)","time":"08:30","court":"1코트","matchNo":"2번","title":"단체전 본선 하이클리어 - 풀리그","status":"경기종료","firstTeam":"왕운클럽","secondTeam":"부영클럽","score":"2 : 3","text":"경기종료 단체전 본선 하이클리어 - 풀리그 왕운클럽 2 : 3 부영클럽 2026.06.20(토) 08:30 1코트 2번 세부경기보기","includesClub":false},{"date":"2026.06.20(토)","time":"09:00","court":"1코트","matchNo":"3번","title":"단체전 본선 하이클리어 - 풀리그","status":"경기종료","firstTeam":"승평클럽","secondTeam":"왕운클럽","score":"3 : 2","text":"경기종료 단체전 본선 하이클리어 - 풀리그 승평클럽 3 : 2 왕운클럽 2026.06.20(토) 09:00 1코트 3번 세부경기보기","includesClub":false}],"sourceUrl":"https://sfa.bkplay.kr/tournament/qualifierMatch?tnmtId=3868&playingCategoryId=98871&groupId=122295"},{"drawId":"98872-122296","tournamentId":"3868","tournamentName":"제22회 순천시생활체육대축전 및 제11회 클럽최강전 배드민턴대회(하이클리어 리그)","tournamentStatus":"종료","tournamentStartDate":"2026.05.31","tournamentEndDate":"2026.06.20","tournamentVenue":"국민체육센터민(합60)","category":{"event":"타입없음","age":"예선","level":"하이클리어","teamCount":12,"playingCategoryId":"98872","title":"타입없음 예선 하이클리어","sourceUrl":"https://sfa.bkplay.kr/tournament/qualifierMatch?tnmtId=3868&playingCategoryId=98872&groupId=122296"},"groupName":"1조","groupId":"122296","matchDate":"05월31일(일)","venue":"국민체육센터민(합60)","standings":[{"rank":null,"teamName":"비봉클럽","players":[],"wins":0,"losses":0,"game":{"scored":0,"conceded":0,"diff":0},"point":{"scored":0,"conceded":0,"diff":0},"includesClub":false,"isCombinedClub":false},{"rank":null,"teamName":"효산클럽","players":[],"wins":0,"losses":0,"game":{"scored":0,"conceded":0,"diff":0},"point":{"scored":0,"conceded":0,"diff":0},"includesClub":false,"isCombinedClub":false},{"rank":null,"teamName":"한올클럽","players":[],"wins":0,"losses":0,"game":{"scored":0,"conceded":0,"diff":0},"point":{"scored":0,"conceded":0,"diff":0},"includesClub":false,"isCombinedClub":false}],"matches":[{"date":"2026.05.31(일)","time":"08:00","court":"1코트","matchNo":"1번","title":"단체전 예선 하이클리어 - 예선","status":"경기예정","firstTeam":"한올클럽","secondTeam":"효산클럽","score":"0 : 0","text":"경기예정 단체전 예선 하이클리어 - 예선 한올클럽 0 : 0 효산클럽 2026.05.31(일) 08:00 1코트 1번 세부경기보기","includesClub":false},{"date":"2026.05.31(일)","time":"09:00","court":"1코트","matchNo":"3번","title":"단체전 예선 하이클리어 - 예선","status":"경기예정","firstTeam":"비봉클럽","secondTeam":"한올클럽","score":"0 : 0","text":"경기예정 단체전 예선 하이클리어 - 예선 비봉클럽 0 : 0 한올클럽 2026.05.31(일) 09:00 1코트 3번 세부경기보기","includesClub":false},{"date":"2026.05.31(일)","time":"10:00","court":"1코트","matchNo":"5번","title":"단체전 예선 하이클리어 - 예선","status":"경기예정","firstTeam":"효산클럽","secondTeam":"비봉클럽","score":"0 : 0","text":"경기예정 단체전 예선 하이클리어 - 예선 효산클럽 0 : 0 비봉클럽 2026.05.31(일) 10:00 1코트 5번 세부경기보기","includesClub":false}],"sourceUrl":"https://sfa.bkplay.kr/tournament/qualifierMatch?tnmtId=3868&playingCategoryId=98872&groupId=122296"},{"drawId":"98872-122297","tournamentId":"3868","tournamentName":"제22회 순천시생활체육대축전 및 제11회 클럽최강전 배드민턴대회(하이클리어 리그)","tournamentStatus":"종료","tournamentStartDate":"2026.05.31","tournamentEndDate":"2026.06.20","tournamentVenue":"국민체육센터민(합60)","category":{"event":"타입없음","age":"예선","level":"하이클리어","teamCount":12,"playingCategoryId":"98872","title":"타입없음 예선 하이클리어","sourceUrl":"https://sfa.bkplay.kr/tournament/qualifierMatch?tnmtId=3868&playingCategoryId=98872&groupId=122297"},"groupName":"2조","groupId":"122297","matchDate":"05월31일(일)","venue":"국민체육센터민(합60)","standings":[{"rank":null,"teamName":"신대클럽","players":[],"wins":0,"losses":0,"game":{"scored":0,"conceded":0,"diff":0},"point":{"scored":0,"conceded":0,"diff":0},"includesClub":false,"isCombinedClub":false},{"rank":null,"teamName":"조례클럽","players":[],"wins":0,"losses":0,"game":{"scored":0,"conceded":0,"diff":0},"point":{"scored":0,"conceded":0,"diff":0},"includesClub":false,"isCombinedClub":false},{"rank":null,"teamName":"향림클럽","players":[],"wins":0,"losses":0,"game":{"scored":0,"conceded":0,"diff":0},"point":{"scored":0,"conceded":0,"diff":0},"includesClub":false,"isCombinedClub":false}],"matches":[{"date":"2026.05.31(일)","time":"08:00","court":"2코트","matchNo":"1번","title":"단체전 예선 하이클리어 - 예선","status":"경기예정","firstTeam":"조례클럽","secondTeam":"향림클럽","score":"0 : 0","text":"경기예정 단체전 예선 하이클리어 - 예선 조례클럽 0 : 0 향림클럽 2026.05.31(일) 08:00 2코트 1번 세부경기보기","includesClub":false},{"date":"2026.05.31(일)","time":"09:00","court":"2코트","matchNo":"3번","title":"단체전 예선 하이클리어 - 예선","status":"경기예정","firstTeam":"신대클럽","secondTeam":"조례클럽","score":"0 : 0","text":"경기예정 단체전 예선 하이클리어 - 예선 신대클럽 0 : 0 조례클럽 2026.05.31(일) 09:00 2코트 3번 세부경기보기","includesClub":false},{"date":"2026.05.31(일)","time":"10:00","court":"2코트","matchNo":"5번","title":"단체전 예선 하이클리어 - 예선","status":"경기예정","firstTeam":"향림클럽","secondTeam":"신대클럽","score":"0 : 0","text":"경기예정 단체전 예선 하이클리어 - 예선 향림클럽 0 : 0 신대클럽 2026.05.31(일) 10:00 2코트 5번 세부경기보기","includesClub":false}],"sourceUrl":"https://sfa.bkplay.kr/tournament/qualifierMatch?tnmtId=3868&playingCategoryId=98872&groupId=122297"},{"drawId":"98872-122298","tournamentId":"3868","tournamentName":"제22회 순천시생활체육대축전 및 제11회 클럽최강전 배드민턴대회(하이클리어 리그)","tournamentStatus":"종료","tournamentStartDate":"2026.05.31","tournamentEndDate":"2026.06.20","tournamentVenue":"국민체육센터민(합60)","category":{"event":"타입없음","age":"예선","level":"하이클리어","teamCount":12,"playingCategoryId":"98872","title":"타입없음 예선 하이클리어","sourceUrl":"https://sfa.bkplay.kr/tournament/qualifierMatch?tnmtId=3868&playingCategoryId=98872&groupId=122298"},"groupName":"3조","groupId":"122298","matchDate":"05월31일(일)","venue":"국민체육센터민(합60)","standings":[{"rank":null,"teamName":"남산클럽","players":[],"wins":0,"losses":0,"game":{"scored":0,"conceded":0,"diff":0},"point":{"scored":0,"conceded":0,"diff":0},"includesClub":false,"isCombinedClub":false},{"rank":null,"teamName":"스카이클럽","players":[],"wins":0,"losses":0,"game":{"scored":0,"conceded":0,"diff":0},"point":{"scored":0,"conceded":0,"diff":0},"includesClub":false,"isCombinedClub":false},{"rank":null,"teamName":"연향클럽","players":[],"wins":0,"losses":0,"game":{"scored":0,"conceded":0,"diff":0},"point":{"scored":0,"conceded":0,"diff":0},"includesClub":false,"isCombinedClub":false}],"matches":[{"date":"2026.05.31(일)","time":"08:30","court":"1코트","matchNo":"2번","title":"단체전 예선 하이클리어 - 예선","status":"경기예정","firstTeam":"연향클럽","secondTeam":"남산클럽","score":"0 : 0","text":"경기예정 단체전 예선 하이클리어 - 예선 연향클럽 0 : 0 남산클럽 2026.05.31(일) 08:30 1코트 2번 세부경기보기","includesClub":false},{"date":"2026.05.31(일)","time":"09:30","court":"1코트","matchNo":"4번","title":"단체전 예선 하이클리어 - 예선","status":"경기예정","firstTeam":"스카이클럽","secondTeam":"연향클럽","score":"0 : 0","text":"경기예정 단체전 예선 하이클리어 - 예선 스카이클럽 0 : 0 연향클럽 2026.05.31(일) 09:30 1코트 4번 세부경기보기","includesClub":false},{"date":"2026.05.31(일)","time":"10:30","court":"1코트","matchNo":"6번","title":"단체전 예선 하이클리어 - 예선","status":"경기예정","firstTeam":"남산클럽","secondTeam":"스카이클럽","score":"0 : 0","text":"경기예정 단체전 예선 하이클리어 - 예선 남산클럽 0 : 0 스카이클럽 2026.05.31(일) 10:30 1코트 6번 세부경기보기","includesClub":false}],"sourceUrl":"https://sfa.bkplay.kr/tournament/qualifierMatch?tnmtId=3868&playingCategoryId=98872&groupId=122298"},{"drawId":"98872-122299","tournamentId":"3868","tournamentName":"제22회 순천시생활체육대축전 및 제11회 클럽최강전 배드민턴대회(하이클리어 리그)","tournamentStatus":"종료","tournamentStartDate":"2026.05.31","tournamentEndDate":"2026.06.20","tournamentVenue":"국민체육센터민(합60)","category":{"event":"타입없음","age":"예선","level":"하이클리어","teamCount":12,"playingCategoryId":"98872","title":"타입없음 예선 하이클리어","sourceUrl":"https://sfa.bkplay.kr/tournament/qualifierMatch?tnmtId=3868&playingCategoryId=98872&groupId=122299"},"groupName":"4조","groupId":"122299","matchDate":"05월31일(일)","venue":"국민체육센터민(합60)","standings":[{"rank":null,"teamName":"왕지클럽","players":[],"wins":0,"losses":0,"game":{"scored":0,"conceded":0,"diff":0},"point":{"scored":0,"conceded":0,"diff":0},"includesClub":false,"isCombinedClub":false},{"rank":null,"teamName":"프라임클럽","players":[],"wins":0,"losses":0,"game":{"scored":0,"conceded":0,"diff":0},"point":{"scored":0,"conceded":0,"diff":0},"includesClub":false,"isCombinedClub":false},{"rank":null,"teamName":"팔마클럽","players":[],"wins":0,"losses":0,"game":{"scored":0,"conceded":0,"diff":0},"point":{"scored":0,"conceded":0,"diff":0},"includesClub":false,"isCombinedClub":false}],"matches":[{"date":"2026.05.31(일)","time":"08:30","court":"2코트","matchNo":"2번","title":"단체전 예선 하이클리어 - 예선","status":"경기예정","firstTeam":"프라임클럽","secondTeam":"팔마클럽","score":"0 : 0","text":"경기예정 단체전 예선 하이클리어 - 예선 프라임클럽 0 : 0 팔마클럽 2026.05.31(일) 08:30 2코트 2번 세부경기보기","includesClub":false},{"date":"2026.05.31(일)","time":"09:30","court":"2코트","matchNo":"4번","title":"단체전 예선 하이클리어 - 예선","status":"경기예정","firstTeam":"왕지클럽","secondTeam":"프라임클럽","score":"0 : 0","text":"경기예정 단체전 예선 하이클리어 - 예선 왕지클럽 0 : 0 프라임클럽 2026.05.31(일) 09:30 2코트 4번 세부경기보기","includesClub":false},{"date":"2026.05.31(일)","time":"10:30","court":"2코트","matchNo":"6번","title":"단체전 예선 하이클리어 - 예선","status":"경기예정","firstTeam":"팔마클럽","secondTeam":"왕지클럽","score":"0 : 0","text":"경기예정 단체전 예선 하이클리어 - 예선 팔마클럽 0 : 0 왕지클럽 2026.05.31(일) 10:30 2코트 6번 세부경기보기","includesClub":false}],"sourceUrl":"https://sfa.bkplay.kr/tournament/qualifierMatch?tnmtId=3868&playingCategoryId=98872&groupId=122299"}]}
